Corekaburra/__init__.py
Corekaburra/__main__.py
Corekaburra/check_inputs.py
Corekaburra/commandline_interface.py
Corekaburra/consesus_core_genome.py
Corekaburra/exit_with_error.py
Corekaburra/gff_parser.py
Corekaburra/merge_dicts.py
Corekaburra/output_writer_functions.py
Corekaburra/parse_gene_presence_absence.py
Corekaburra/read_complete_genome_file.py
Corekaburra/summary_table.py
Corekaburra-0.0.5.dist-info/LICENSE
Corekaburra-0.0.5.dist-info/METADATA
Corekaburra-0.0.5.dist-info/WHEEL
Corekaburra-0.0.5.dist-info/entry_points.txt
Corekaburra-0.0.5.dist-info/top_level.txt
Corekaburra-0.0.5.dist-info/RECORD
