Metadata-Version: 2.1
Name: Corekaburra
Version: 0.0.5
Summary: A commandline bioinformatics tool to utilize syntenic information from genomes in the context of pan-genomes
Home-page: https://github.com/milnus/Corekaburra
Author: Magnus Ganer Jespersen
Author-email: magnus.ganer.j@gmail.com
License: LICENSE
Keywords: Genomics,pan-genome,bacteria,prokaryotes,bioinformatics
Classifier: Programming Language :: Python :: 3.9
Classifier: License :: OSI Approved :: MIT License
Classifier: Intended Audience :: Science/Research
Classifier: Topic :: Scientific/Engineering :: Bio-Informatics
Classifier: Development Status :: 4 - Beta
License-File: LICENSE
Requires-Dist: biopython (==1.79)
Requires-Dist: networkx (>=2.6.3)
Requires-Dist: gffutils (>=0.10.1)
Requires-Dist: numpy (>=1.23.4)
